{"user_name":"Dustin","user_username":"qrnan","user_bio":"","user_links":"","user_avatar":"https://gravatar.com/avatar/99d8c1104197ff7c022102af604759839ca07cc538dea351e673f4c84c98e985?r=pg&d=retro&size=200","url":"https://n8nworkflows.xyz/workflows/create-daily-youtube-playlist--using-google-sheets--and-get-notified-in-telegram-3077\n","url_n8n":"https://n8n.io/workflows/3077","nodeTypes":{"n8n-nodes-base.filter":{"count":1},"n8n-nodes-base.youTube":{"count":3},"n8n-nodes-base.splitOut":{"count":1},"n8n-nodes-base.telegram":{"count":1},"n8n-nodes-base.stickyNote":{"count":8},"n8n-nodes-base.httpRequest":{"count":2},"n8n-nodes-base.googleSheets":{"count":5},"n8n-nodes-base.manualTrigger":{"count":1},"n8n-nodes-base.scheduleTrigger":{"count":1}},"categories":[{"id":11,"name":"Other"}]}