{"user_name":"Łukasz","user_username":"lukaszpp","user_bio":"Developer, automation architect and CTO/CEO helping businesses turn complex processes into scalable systems. I build smart automations and SaaS solutions for Real Estate, advertising, logistics and more.\n\nMy focus is to remove manual work, increase efficiency, and create measurable business impact.\n\nI support founders and decision-makers in turning ideas into structured, automated operations.\n\nLet’s connect 🤝","user_links":"https://sailingbyte.com","user_avatar":"https://gravatar.com/avatar/aae1a29225cc13556a92db7f75050da4bb664bf68e1d73407da6c9cd5a7a9a8a?r=pg&d=retro&size=200","url":"https://n8nworkflows.xyz/workflows/clone-nocodb-tables-and-data-to-another-base-15373\n","url_n8n":"https://n8n.io/workflows/15373","nodeTypes":{"n8n-nodes-base.set":{"count":2},"n8n-nodes-base.switch":{"count":1},"n8n-nodes-base.splitOut":{"count":1},"n8n-nodes-base.stickyNote":{"count":4},"n8n-nodes-base.httpRequest":{"count":4},"n8n-nodes-base.manualTrigger":{"count":1},"n8n-nodes-base.splitInBatches":{"count":2}},"categories":[{"id":36,"name":"File Management"}]}